pylsp_autoimport/__init__.py
pylsp_autoimport/plugin.py
pylsp_autoimport-0.1.0.dist-info/entry_points.txt
pylsp_autoimport-0.1.0.dist-info/LICENSE
pylsp_autoimport-0.1.0.dist-info/WHEEL
pylsp_autoimport-0.1.0.dist-info/METADATA
pylsp_autoimport-0.1.0.dist-info/RECORD
