Metadata-Version: 2.1
Name: pylsp-autoimport
Version: 0.1.0
Summary: 
License: GPLv3
Author: bageljr
Author-email: bageljr897@protonmail.com
Requires-Python: >=3.7,<4.0
Classifier: License :: Other/Proprietary License
Classifier: Programming Language :: Python :: 3
Classifier: Programming Language :: Python :: 3.10
Classifier: Programming Language :: Python :: 3.7
Classifier: Programming Language :: Python :: 3.8
Classifier: Programming Language :: Python :: 3.9
Requires-Dist: autoimport (>=1.2.2,<2.0.0)
Requires-Dist: python-lsp-server (>=1.4.1,<2.0.0)
